SupCL_Seq/SupCsTrainer.py
SupCL_Seq/__init__.py
SupCL_Seq-0.0.1.dist-info/LICENSE
SupCL_Seq-0.0.1.dist-info/METADATA
SupCL_Seq-0.0.1.dist-info/WHEEL
SupCL_Seq-0.0.1.dist-info/top_level.txt
SupCL_Seq-0.0.1.dist-info/RECORD
