Metadata-Version: 2.1
Name: SupCL-Seq
Version: 0.0.1
Summary: Supervised Contrastive Learning for Downstream Optimized Sequence representations
Home-page: https://github.com/hooman650/SupCL-Seq
Author: Hooman
Author-email: hooman650@yahoo.com
License: UNKNOWN
Project-URL: Bug Tracker, https://github.com/hooman650/SupCL-Seq/issues
Platform: UNKNOWN
Classifier: Programming Language :: Python :: 3
Classifier: License :: OSI Approved :: MIT License
Classifier: Operating System :: OS Independent
Requires-Python: >=3.6
License-File: LICENSE
